mdp/__init__.py
mdp/decode.py
mdp/prettyprinter.py
mdp/secdef.py
mdp/orderbook/__init__.py
mdp/orderbook/orderbook.py
mdp/orderbook/packet_processor.py
sbedecoder/__init__.py
sbedecoder/generated.py
sbedecoder/message.py
sbedecoder/parser.py
sbedecoder/schema.py
sbedecoder-0.1.10.data/scripts/mdp_base64_decoder.py
sbedecoder-0.1.10.data/scripts/mdp_book_builder.py
sbedecoder-0.1.10.data/scripts/mdp_decoder.py
sbedecoder-0.1.10.dist-info/LICENSE.txt
sbedecoder-0.1.10.dist-info/METADATA
sbedecoder-0.1.10.dist-info/WHEEL
sbedecoder-0.1.10.dist-info/top_level.txt
sbedecoder-0.1.10.dist-info/RECORD
