Metadata-Version: 2.1
Name: sbedecoder
Version: 0.1.10
Summary: Simple Binary Encoding (SBE) decoder (handles CME MDP3 messages)
Home-page: https://github.com/tfgm/sbedecoder
Author: TradeForecaster Global Markets, LLC
Author-email: github@tradeforecaster.com
License: MIT
Keywords: sbe mdp3 orderbook message decoder
Platform: UNKNOWN
Classifier: License :: OSI Approved :: MIT License
Classifier: Programming Language :: Python :: 2
Classifier: Programming Language :: Python :: 2.7
Classifier: Programming Language :: Python :: 3
Classifier: Programming Language :: Python :: 3.6
Requires-Dist: dpkt
Requires-Dist: lxml
Requires-Dist: six
